boutiques/__init__.py
boutiques/__version__.py
boutiques/bids.py
boutiques/bosh.py
boutiques/boshParsers.py
boutiques/conftest.py
boutiques/creator.py
boutiques/dataHandler.py
boutiques/deprecate.py
boutiques/descriptor2func.py
boutiques/evaluate.py
boutiques/exporter.py
boutiques/importer.py
boutiques/invocationSchemaHandler.py
boutiques/localExec.py
boutiques/logger.py
boutiques/nexusHelper.py
boutiques/prettyprint.py
boutiques/publisher.py
boutiques/puller.py
boutiques/searcher.py
boutiques/test.py
boutiques/validator.py
boutiques/zenodoHelper.py
boutiques/schema/README.md
boutiques/schema/descriptor.schema.json
boutiques/schema/examples/README.md
boutiques/schema/examples/example1/Dockerfile
boutiques/schema/examples/example1/example1_docker.json
boutiques/schema/examples/example1/exampleTool1.py
boutiques/schema/examples/example1/exampleTool1_nonutf8.py
boutiques/schema/examples/example1/invocation.json
boutiques/schema/examples/example2/example2.json
boutiques/schema/examples/example2/invocation.json
boutiques/schema/examples/example3/example3.json
boutiques/schema/examples/example3/invocation.json
boutiques/schema/examples/fsl_bet/example_complete_invocation.json
boutiques/schema/examples/fsl_bet/example_invocation.json
boutiques/schema/examples/fsl_bet/fsl_bet.json
boutiques/templates/basic.json
boutiques/templates/bids-app.json
boutiques/templates/ordered_keys_desc.json
boutiques/tests/BaseTest.py
boutiques/tests/README.md
boutiques/tests/boutiques_mocks.py
boutiques/tests/test_bids.py
boutiques/tests/test_bosh.py
boutiques/tests/test_crash_python3.py
boutiques/tests/test_creator.py
boutiques/tests/test_data_collection.py
boutiques/tests/test_data_handler.py
boutiques/tests/test_deprecate.py
boutiques/tests/test_evaluate.py
boutiques/tests/test_example.py
boutiques/tests/test_example1.py
boutiques/tests/test_example2.py
boutiques/tests/test_example3.py
boutiques/tests/test_example_flag.py
boutiques/tests/test_exec.py
boutiques/tests/test_export.py
boutiques-0.5.31.dist-info/METADATA
boutiques-0.5.31.dist-info/WHEEL
boutiques-0.5.31.dist-info/entry_points.txt
boutiques-0.5.31.dist-info/licenses/LICENSE
boutiques-0.5.31.dist-info/RECORD
