Metadata-Version: 2.4
Name: boutiques
Version: 0.5.31
Summary: Schema for describing bash command-line tools
Project-URL: Homepage, http://github.com/boutiques/boutiques
Author-email: Tristan Glatard <tristan.glatard@concordia.ca>, Gregory Kiar <gkiar07@gmail.com>
License: MIT
License-File: LICENSE
Classifier: License :: OSI Approved :: MIT License
Classifier: Natural Language :: English
Classifier: Operating System :: OS Independent
Classifier: Programming Language :: Python
Classifier: Programming Language :: Python :: 3
Classifier: Programming Language :: Python :: 3.9
Classifier: Programming Language :: Python :: 3.10
Classifier: Programming Language :: Python :: 3.11
Classifier: Programming Language :: Python :: 3.12
Classifier: Programming Language :: Python :: 3.13
Classifier: Topic :: Software Development :: Libraries :: Python Modules
Requires-Python: >=3.9
Requires-Dist: jsonschema
Requires-Dist: simplejson
Requires-Dist: tabulate
Requires-Dist: termcolor
Provides-Extra: all
Requires-Dist: docopt; extra == 'all'
Requires-Dist: mock; extra == 'all'
Requires-Dist: nexus-sdk; extra == 'all'
Requires-Dist: oyaml; extra == 'all'
Requires-Dist: pytest-cov; extra == 'all'
Requires-Dist: pytest-runner; extra == 'all'
Requires-Dist: pytest>=6.0.0; extra == 'all'
Requires-Dist: requests; extra == 'all'
Requires-Dist: toml; extra == 'all'
Provides-Extra: doc
Requires-Dist: sphinx-argparse; extra == 'doc'
Requires-Dist: sphinx-rtd-theme; extra == 'doc'
Provides-Extra: test
Requires-Dist: pytest-cov; extra == 'test'
Requires-Dist: pytest-runner; extra == 'test'
Requires-Dist: pytest>=6.0.0; extra == 'test'
